Metadata-Version: 1.0
Name: BayesBands
Version: 0.0.2
Summary: Plots confidence bands for cross section calculations
Home-page: UNKNOWN
Author: Amy
Author-email: lovellam@msu.edu
License: UNKNOWN
Platform: UNKNOWN
